datacollector/__init__.py
datacollector/config.py
datacollector/google_analytics.py
datacollector/pagespeed.py
datacollector/raw_data_to_csv.py
datacollector/screaming_frog.py
datacollector/semrush_api.py
itwingsdatacollector-0.2.dist-info/LICENSE
itwingsdatacollector-0.2.dist-info/METADATA
itwingsdatacollector-0.2.dist-info/WHEEL
itwingsdatacollector-0.2.dist-info/top_level.txt
itwingsdatacollector-0.2.dist-info/RECORD
