Metadata-Version: 2.1
Name: itwingsdatacollector
Version: 0.2
Summary: 'IT Wings Data Collector: A tool for collecting diverse data sources for insights',
Author: Mayank
Author-email: mayanktimbadia@gmail.com
Classifier: Programming Language :: Python :: 3
Classifier: License :: OSI Approved :: MIT License
Classifier: Operating System :: OS Independent
Requires-Python: >=3.6
License-File: LICENSE
